adaptsapi/__init__.py
adaptsapi/cli.py
adaptsapi/config.py
adaptsapi/generate_docs.py
adaptsapi-0.1.9.dist-info/licenses/LICENSE
adaptsapi-0.1.9.dist-info/METADATA
adaptsapi-0.1.9.dist-info/WHEEL
adaptsapi-0.1.9.dist-info/entry_points.txt
adaptsapi-0.1.9.dist-info/top_level.txt
adaptsapi-0.1.9.dist-info/RECORD
