Metadata-Version: 2.4
Name: adaptsapi
Version: 0.1.9
Summary: CLI to enqueue triggers via internal API Gateway → SNS
Home-page: https://github.com/adaptsai/adaptsapi
Author: adapts
Author-email: "VerifyAI Inc." <dev@adapts.ai>
License-Expression: LicenseRef-Proprietary
Project-URL: Homepage, https://adapts.ai/
Project-URL: Source, https://github.com/AdaptsAI/adapts_api_client
Keywords: adapts,api,cli,sns
Classifier: Programming Language :: Python :: 3
Classifier: Operating System :: OS Independent
Requires-Python: >=3.10
License-File: LICENSE
Requires-Dist: requests
Dynamic: author
Dynamic: home-page
Dynamic: license-file
Dynamic: requires-python
